CHANGES.rst
CONTRIBUTORS.rst
MANIFEST.in
README.rst
setup.cfg
setup.py
docs/LICENSE.GPL
docs/LICENSE.rst
docs/index.rst
src/collective/__init__.py
src/collective.facebook.instantarticles.egg-info/PKG-INFO
src/collective.facebook.instantarticles.egg-info/SOURCES.txt
src/collective.facebook.instantarticles.egg-info/dependency_links.txt
src/collective.facebook.instantarticles.egg-info/entry_points.txt
src/collective.facebook.instantarticles.egg-info/namespace_packages.txt
src/collective.facebook.instantarticles.egg-info/not-zip-safe
src/collective.facebook.instantarticles.egg-info/requires.txt
src/collective.facebook.instantarticles.egg-info/top_level.txt
src/collective/facebook/__init__.py
src/collective/facebook/instantarticles/__init__.py
src/collective/facebook/instantarticles/configure.zcml
src/collective/facebook/instantarticles/interfaces.py
src/collective/facebook/instantarticles/setuphandlers.py
src/collective/facebook/instantarticles/testing.py
src/collective/facebook/instantarticles/browser/__init__.py
src/collective/facebook/instantarticles/browser/configure.zcml
src/collective/facebook/instantarticles/browser/controlpanel.py
src/collective/facebook/instantarticles/browser/instant_article_view.py
src/collective/facebook/instantarticles/browser/rss_view.py
src/collective/facebook/instantarticles/browser/viewlets.py
src/collective/facebook/instantarticles/browser/static/.gitkeep
src/collective/facebook/instantarticles/browser/static/fb_zap.png
src/collective/facebook/instantarticles/browser/templates/instant_article_view.pt
src/collective/facebook/instantarticles/browser/templates/instant_article_viewlet.pt
src/collective/facebook/instantarticles/browser/templates/rss_view.pt
src/collective/facebook/instantarticles/locales/collective.facebook.instantarticles.pot
src/collective/facebook/instantarticles/locales/update.sh
src/collective/facebook/instantarticles/locales/it/LC_MESSAGES/collective.facebook.instantarticles.mo
src/collective/facebook/instantarticles/locales/it/LC_MESSAGES/collective.facebook.instantarticles.po
src/collective/facebook/instantarticles/profiles/default/browserlayer.xml
src/collective/facebook/instantarticles/profiles/default/controlpanel.xml
src/collective/facebook/instantarticles/profiles/default/metadata.xml
src/collective/facebook/instantarticles/profiles/default/registry.xml
src/collective/facebook/instantarticles/profiles/uninstall/browserlayer.xml
src/collective/facebook/instantarticles/profiles/uninstall/registry.xml
