Metadata-Version: 2.1
Name: collective.facebook.instantarticles
Version: 1.0.1
Summary: Plone plugin for Facebook's instant articles integration
Home-page: https://github.com/collective/collective.facebook.instantarticles
Author: RedTurtle Technology
Author-email: sviluppoplone@redturtle.it
License: GPL version 2
Keywords: Python Plone facebook instantarticles
Platform: UNKNOWN
Classifier: Environment :: Web Environment
Classifier: Framework :: Plone
Classifier: Framework :: Plone :: 4.0
Classifier: Framework :: Plone :: 4.3
Classifier: Programming Language :: Python
Classifier: Programming Language :: Python :: 2.7
Classifier: Operating System :: OS Independent
Classifier: License :: OSI Approved :: GNU General Public License v2 (GPLv2)
Provides-Extra: test
